meitner/__init__.py
meitner/_version.py
meitner/auditevents.py
meitner/basesdk.py
meitner/employeeplacements.py
meitner/employees.py
meitner/groups.py
meitner/guardians.py
meitner/httpclient.py
meitner/py.typed
meitner/schools.py
meitner/sdk.py
meitner/sdkconfiguration.py
meitner/studentplacements.py
meitner/students.py
meitner/_hooks/__init__.py
meitner/_hooks/registration.py
meitner/_hooks/sdkhooks.py
meitner/_hooks/types.py
meitner/errors/__init__.py
meitner/errors/auditeventsearch422responsebody_error.py
meitner/errors/employeecreate422responsebody_error.py
meitner/errors/employeeplacementcreate422responsebody_error.py
meitner/errors/employeeplacementsearch422responsebody_error.py
meitner/errors/employeeplacementupdate422responsebody_error.py
meitner/errors/employeesearch422responsebody_error.py
meitner/errors/employeeupdate422responsebody_error.py
meitner/errors/error400responsebody.py
meitner/errors/error401responsebody.py
meitner/errors/error403responsebody.py
meitner/errors/error404responsebody.py
meitner/errors/error409responsebody.py
meitner/errors/error429responsebody.py
meitner/errors/error500responsebody.py
meitner/errors/groupcreate422responsebody_error.py
meitner/errors/groupsearch422responsebody_error.py
meitner/errors/groupupdate422responsebody_error.py
meitner/errors/guardiancreate422responsebody_error.py
meitner/errors/guardiansearch422responsebody_error.py
meitner/errors/guardianupdate422responsebody_error.py
meitner/errors/meitnerdefaulterror.py
meitner/errors/meitnererror.py
meitner/errors/no_response_error.py
meitner/errors/responsevalidationerror.py
meitner/errors/schoolcreate422responsebody_error.py
meitner/errors/schoolsearch422responsebody_error.py
meitner/errors/schoolupdate422responsebody_error.py
meitner/errors/studentcreate422responsebody_error.py
meitner/errors/studentplacementcreate422responsebody_error.py
meitner/errors/studentplacementsearch422responsebody_error.py
meitner/errors/studentplacementupdate422responsebody_error.py
meitner-0.4.0.dist-info/METADATA
meitner-0.4.0.dist-info/WHEEL
meitner-0.4.0.dist-info/top_level.txt
meitner-0.4.0.dist-info/RECORD
